<annotation>
	<folder>Peach___Bacterial_spot</folder>
	<filename>04a76261-3ba2-46b7-b604-7517baac2505___Rut._Bact.S 1517.JPG</filename>
	<path>C:\Users\TimmySagacity\Desktop\Plant diseases\PlantVillage\train\Peach___Bacterial_spot\04a76261-3ba2-46b7-b604-7517baac2505___Rut._Bact.S 1517.JPG</path>
	<source>
		<database>Unknown</database>
	</source>
	<size>
		<width>256</width>
		<height>256</height>
		<depth>3</depth>
	</size>
	<segmented>0</segmented>
	<object>
		<name>pbs</name>
		<pose>Unspecified</pose>
		<truncated>0</truncated>
		<difficult>0</difficult>
		<bndbox>
			<xmin>5</xmin>
			<ymin>6</ymin>
			<xmax>208</xmax>
			<ymax>103</ymax>
		</bndbox>
	</object>
	<object>
		<name>pbs</name>
		<pose>Unspecified</pose>
		<truncated>1</truncated>
		<difficult>0</difficult>
		<bndbox>
			<xmin>65</xmin>
			<ymin>104</ymin>
			<xmax>256</xmax>
			<ymax>253</ymax>
		</bndbox>
	</object>
</annotation>
