<annotation>
	<folder>Tomato___healthy</folder>
	<filename>0d70d565-520e-474c-85c1-ab478c9f1d4b___GH_HL Leaf 203.JPG</filename>
	<path>C:\Users\TimmySagacity\Desktop\Plant diseases\PlantVillage\train\Tomato___healthy\0d70d565-520e-474c-85c1-ab478c9f1d4b___GH_HL Leaf 203.1.JPG</path>
	<source>
		<database>Unknown</database>
	</source>
	<size>
		<width>256</width>
		<height>256</height>
		<depth>3</depth>
	</size>
	<segmented>0</segmented>
	<object>
		<name>tom_h</name>
		<pose>Unspecified</pose>
		<truncated>0</truncated>
		<difficult>0</difficult>
		<bndbox>
			<xmin>34</xmin>
			<ymin>100</ymin>
			<xmax>233</xmax>
			<ymax>217</ymax>
		</bndbox>
	</object>
	<object>
		<name>tom_h</name>
		<pose>Unspecified</pose>
		<truncated>0</truncated>
		<difficult>0</difficult>
		<bndbox>
			<xmin>46</xmin>
			<ymin>8</ymin>
			<xmax>204</xmax>
			<ymax>100</ymax>
		</bndbox>
	</object>
</annotation>
