<annotation>
	<folder>Tomato___Tomato_Yellow_Leaf_Curl_Virus</folder>
	<filename>0f4764d2-a42c-4c17-8a9c-a38adb04a9a1___UF.GRC_YLCV_Lab 09615.JPG</filename>
	<path>C:\Users\TimmySagacity\Desktop\Plant diseases\PlantVillage\train\Tomato___Tomato_Yellow_Leaf_Curl_Virus\0f4764d2-a42c-4c17-8a9c-a38adb04a9a1___UF.GRC_YLCV_Lab 09615.JPG</path>
	<source>
		<database>Unknown</database>
	</source>
	<size>
		<width>256</width>
		<height>256</height>
		<depth>3</depth>
	</size>
	<segmented>0</segmented>
	<object>
		<name>t_ty</name>
		<pose>Unspecified</pose>
		<truncated>0</truncated>
		<difficult>0</difficult>
		<bndbox>
			<xmin>26</xmin>
			<ymin>150</ymin>
			<xmax>126</xmax>
			<ymax>197</ymax>
		</bndbox>
	</object>
	<object>
		<name>t_ty</name>
		<pose>Unspecified</pose>
		<truncated>0</truncated>
		<difficult>0</difficult>
		<bndbox>
			<xmin>107</xmin>
			<ymin>12</ymin>
			<xmax>236</xmax>
			<ymax>197</ymax>
		</bndbox>
	</object>
</annotation>
