<annotation>
	<folder>Grape___Black_rot</folder>
	<filename>3b905cf5-c442-4d50-bb83-3caf6142d726___FAM_B.Rot 2995.JPG</filename>
	<path>C:\Users\TimmySagacity\Desktop\Plant diseases\PlantVillage\train\Grape___Black_rot\3b905cf5-c442-4d50-bb83-3caf6142d726___FAM_B.Rot 2995.JPG</path>
	<source>
		<database>Unknown</database>
	</source>
	<size>
		<width>256</width>
		<height>256</height>
		<depth>3</depth>
	</size>
	<segmented>0</segmented>
	<object>
		<name>g_br</name>
		<pose>Unspecified</pose>
		<truncated>0</truncated>
		<difficult>0</difficult>
		<bndbox>
			<xmin>23</xmin>
			<ymin>55</ymin>
			<xmax>209</xmax>
			<ymax>237</ymax>
		</bndbox>
	</object>
</annotation>
