<annotation>
	<folder>Grape___Black_rot</folder>
	<filename>3f70c9d3-cf8a-43c3-87e3-c7a788579e7a___FAM_B.Rot 3534.JPG</filename>
	<path>C:\Users\TimmySagacity\Desktop\Plant diseases\PlantVillage\train\Grape___Black_rot\3f70c9d3-cf8a-43c3-87e3-c7a788579e7a___FAM_B.Rot 3534.JPG</path>
	<source>
		<database>Unknown</database>
	</source>
	<size>
		<width>256</width>
		<height>256</height>
		<depth>3</depth>
	</size>
	<segmented>0</segmented>
	<object>
		<name>g_br</name>
		<pose>Unspecified</pose>
		<truncated>0</truncated>
		<difficult>0</difficult>
		<bndbox>
			<xmin>80</xmin>
			<ymin>133</ymin>
			<xmax>210</xmax>
			<ymax>219</ymax>
		</bndbox>
	</object>
	<object>
		<name>g_br</name>
		<pose>Unspecified</pose>
		<truncated>0</truncated>
		<difficult>0</difficult>
		<bndbox>
			<xmin>105</xmin>
			<ymin>35</ymin>
			<xmax>233</xmax>
			<ymax>102</ymax>
		</bndbox>
	</object>
</annotation>
