<annotation>
	<folder>Tomato___Septoria_leaf_spot</folder>
	<filename>4a07823f-bbfe-4880-bbae-59fd1ae9de33___Matt.S_CG 6687.JPG</filename>
	<path>C:\Users\TimmySagacity\Desktop\Plant diseases\PlantVillage\train\Tomato___Septoria_leaf_spot\4a07823f-bbfe-4880-bbae-59fd1ae9de33___Matt.S_CG 6687.JPG</path>
	<source>
		<database>Unknown</database>
	</source>
	<size>
		<width>256</width>
		<height>256</height>
		<depth>3</depth>
	</size>
	<segmented>0</segmented>
	<object>
		<name>t_sLs</name>
		<pose>Unspecified</pose>
		<truncated>0</truncated>
		<difficult>0</difficult>
		<bndbox>
			<xmin>23</xmin>
			<ymin>12</ymin>
			<xmax>90</xmax>
			<ymax>115</ymax>
		</bndbox>
	</object>
	<object>
		<name>t_sLs</name>
		<pose>Unspecified</pose>
		<truncated>0</truncated>
		<difficult>0</difficult>
		<bndbox>
			<xmin>62</xmin>
			<ymin>115</ymin>
			<xmax>154</xmax>
			<ymax>200</ymax>
		</bndbox>
	</object>
	<object>
		<name>t_sLs</name>
		<pose>Unspecified</pose>
		<truncated>0</truncated>
		<difficult>0</difficult>
		<bndbox>
			<xmin>120</xmin>
			<ymin>201</ymin>
			<xmax>190</xmax>
			<ymax>229</ymax>
		</bndbox>
	</object>
</annotation>
