<annotation>
	<folder>Tomato___Bacterial_spot</folder>
	<filename>4a9819e9-6651-480a-a524-74d149449538___GCREC_Bact.Sp 3748.JPG</filename>
	<path>C:\Users\TimmySagacity\Desktop\Plant diseases\PlantVillage\train\Tomato___Bacterial_spot\4a9819e9-6651-480a-a524-74d149449538___GCREC_Bact.Sp 3748.JPG</path>
	<source>
		<database>Unknown</database>
	</source>
	<size>
		<width>256</width>
		<height>256</height>
		<depth>3</depth>
	</size>
	<segmented>0</segmented>
	<object>
		<name>tom_bs</name>
		<pose>Unspecified</pose>
		<truncated>1</truncated>
		<difficult>0</difficult>
		<bndbox>
			<xmin>5</xmin>
			<ymin>5</ymin>
			<xmax>251</xmax>
			<ymax>256</ymax>
		</bndbox>
	</object>
</annotation>
