<annotation>
	<folder>Grape___Black_rot</folder>
	<filename>68318beb-9638-494e-af5f-ef82c30943f2___FAM_B.Rot 0764.JPG</filename>
	<path>C:\Users\TimmySagacity\Desktop\Plant diseases\PlantVillage\train\Grape___Black_rot\68318beb-9638-494e-af5f-ef82c30943f2___FAM_B.Rot 0764.JPG</path>
	<source>
		<database>Unknown</database>
	</source>
	<size>
		<width>256</width>
		<height>256</height>
		<depth>3</depth>
	</size>
	<segmented>0</segmented>
	<object>
		<name>g_br</name>
		<pose>Unspecified</pose>
		<truncated>0</truncated>
		<difficult>0</difficult>
		<bndbox>
			<xmin>70</xmin>
			<ymin>41</ymin>
			<xmax>179</xmax>
			<ymax>119</ymax>
		</bndbox>
	</object>
	<object>
		<name>g_br</name>
		<pose>Unspecified</pose>
		<truncated>0</truncated>
		<difficult>0</difficult>
		<bndbox>
			<xmin>34</xmin>
			<ymin>161</ymin>
			<xmax>92</xmax>
			<ymax>242</ymax>
		</bndbox>
	</object>
	<object>
		<name>g_br</name>
		<pose>Unspecified</pose>
		<truncated>0</truncated>
		<difficult>0</difficult>
		<bndbox>
			<xmin>138</xmin>
			<ymin>149</ymin>
			<xmax>192</xmax>
			<ymax>218</ymax>
		</bndbox>
	</object>
</annotation>
