<annotation>
	<folder>Peach___Bacterial_spot</folder>
	<filename>71c0a139-7c04-405f-a753-0a93a2914b9c___Rutg._Bact.S 1509.JPG</filename>
	<path>C:\Users\TimmySagacity\Desktop\Plant diseases\PlantVillage\train\Peach___Bacterial_spot\71c0a139-7c04-405f-a753-0a93a2914b9c___Rutg._Bact.S 1509.JPG</path>
	<source>
		<database>Unknown</database>
	</source>
	<size>
		<width>256</width>
		<height>256</height>
		<depth>3</depth>
	</size>
	<segmented>0</segmented>
	<object>
		<name>pbs</name>
		<pose>Unspecified</pose>
		<truncated>0</truncated>
		<difficult>0</difficult>
		<bndbox>
			<xmin>12</xmin>
			<ymin>11</ymin>
			<xmax>179</xmax>
			<ymax>93</ymax>
		</bndbox>
	</object>
	<object>
		<name>pbs</name>
		<pose>Unspecified</pose>
		<truncated>0</truncated>
		<difficult>0</difficult>
		<bndbox>
			<xmin>72</xmin>
			<ymin>92</ymin>
			<xmax>231</xmax>
			<ymax>159</ymax>
		</bndbox>
	</object>
	<object>
		<name>pbs</name>
		<pose>Unspecified</pose>
		<truncated>0</truncated>
		<difficult>0</difficult>
		<bndbox>
			<xmin>140</xmin>
			<ymin>158</ymin>
			<xmax>248</xmax>
			<ymax>245</ymax>
		</bndbox>
	</object>
</annotation>
