<annotation>
	<folder>Grape___Esca_(Black_Measles)</folder>
	<filename>7272a251-7c94-4550-8b0d-9f948c1c49a2___FAM_B.Msls 4418.JPG</filename>
	<path>C:\Users\TimmySagacity\Desktop\Plant diseases\PlantVillage\train\Grape___Esca_(Black_Measles)\7272a251-7c94-4550-8b0d-9f948c1c49a2___FAM_B.Msls 4418.JPG</path>
	<source>
		<database>Unknown</database>
	</source>
	<size>
		<width>256</width>
		<height>256</height>
		<depth>3</depth>
	</size>
	<segmented>0</segmented>
	<object>
		<name>g_ebm</name>
		<pose>Unspecified</pose>
		<truncated>0</truncated>
		<difficult>0</difficult>
		<bndbox>
			<xmin>40</xmin>
			<ymin>60</ymin>
			<xmax>213</xmax>
			<ymax>241</ymax>
		</bndbox>
	</object>
</annotation>
