<annotation>
	<folder>Cherry_(including_sour)___healthy</folder>
	<filename>8fbf0127-e286-466a-bb84-9d16e223953a___JR_HL 9459.JPG</filename>
	<path>C:\Users\TimmySagacity\Desktop\Plant diseases\PlantVillage\train\Cherry_(including_sour)___healthy\8fbf0127-e286-466a-bb84-9d16e223953a___JR_HL 9459.JPG</path>
	<source>
		<database>Unknown</database>
	</source>
	<size>
		<width>256</width>
		<height>256</height>
		<depth>3</depth>
	</size>
	<segmented>0</segmented>
	<object>
		<name>ch</name>
		<pose>Unspecified</pose>
		<truncated>0</truncated>
		<difficult>0</difficult>
		<bndbox>
			<xmin>21</xmin>
			<ymin>84</ymin>
			<xmax>217</xmax>
			<ymax>212</ymax>
		</bndbox>
	</object>
	<object>
		<name>ch</name>
		<pose>Unspecified</pose>
		<truncated>0</truncated>
		<difficult>0</difficult>
		<bndbox>
			<xmin>43</xmin>
			<ymin>4</ymin>
			<xmax>200</xmax>
			<ymax>92</ymax>
		</bndbox>
	</object>
</annotation>
