<annotation>
	<folder>Tomato___Target_Spot</folder>
	<filename>997dc7c6-4de8-40d8-8259-d22bc70d2f48___Com.G_TgS_FL 8153.JPG</filename>
	<path>C:\Users\TimmySagacity\Desktop\Plant diseases\PlantVillage\train\Tomato___Target_Spot\997dc7c6-4de8-40d8-8259-d22bc70d2f48___Com.G_TgS_FL 8153.JPG</path>
	<source>
		<database>Unknown</database>
	</source>
	<size>
		<width>256</width>
		<height>256</height>
		<depth>3</depth>
	</size>
	<segmented>0</segmented>
	<object>
		<name>t_ts</name>
		<pose>Unspecified</pose>
		<truncated>0</truncated>
		<difficult>0</difficult>
		<bndbox>
			<xmin>43</xmin>
			<ymin>164</ymin>
			<xmax>183</xmax>
			<ymax>254</ymax>
		</bndbox>
	</object>
	<object>
		<name>t_ts</name>
		<pose>Unspecified</pose>
		<truncated>0</truncated>
		<difficult>0</difficult>
		<bndbox>
			<xmin>69</xmin>
			<ymin>69</ymin>
			<xmax>169</xmax>
			<ymax>165</ymax>
		</bndbox>
	</object>
</annotation>
