<annotation>
	<folder>Apple___Black_rot</folder>
	<filename>a97c2088-9bf7-4840-8a41-813aadae4aa6___JR_FrgE.S 2793.JPG</filename>
	<path>C:\Users\TimmySagacity\Desktop\Plant diseases\PlantVillage\train\Apple___Black_rot\a97c2088-9bf7-4840-8a41-813aadae4aa6___JR_FrgE.S 2793.JPG</path>
	<source>
		<database>Unknown</database>
	</source>
	<size>
		<width>256</width>
		<height>256</height>
		<depth>3</depth>
	</size>
	<segmented>0</segmented>
	<object>
		<name>abr</name>
		<pose>Unspecified</pose>
		<truncated>0</truncated>
		<difficult>0</difficult>
		<bndbox>
			<xmin>23</xmin>
			<ymin>12</ymin>
			<xmax>236</xmax>
			<ymax>198</ymax>
		</bndbox>
	</object>
</annotation>
