<annotation>
	<folder>Cherry_(including_sour)___healthy</folder>
	<filename>ab3bea0d-8559-4f2b-ad4b-3dec4bc43036___JR_HL 9467.JPG</filename>
	<path>C:\Users\TimmySagacity\Desktop\Plant diseases\PlantVillage\train\Cherry_(including_sour)___healthy\ab3bea0d-8559-4f2b-ad4b-3dec4bc43036___JR_HL 9467.JPG</path>
	<source>
		<database>Unknown</database>
	</source>
	<size>
		<width>256</width>
		<height>256</height>
		<depth>3</depth>
	</size>
	<segmented>0</segmented>
	<object>
		<name>ch</name>
		<pose>Unspecified</pose>
		<truncated>0</truncated>
		<difficult>0</difficult>
		<bndbox>
			<xmin>23</xmin>
			<ymin>3</ymin>
			<xmax>204</xmax>
			<ymax>197</ymax>
		</bndbox>
	</object>
</annotation>
