<annotation>
	<folder>Cherry_(including_sour)___healthy</folder>
	<filename>050b598c-9105-4838-8996-101568d6941e___JR_HL 9732.JPG</filename>
	<path>C:\Users\TimmySagacity\Desktop\Plant diseases\PlantVillage\train\Cherry_(including_sour)___healthy\050b598c-9105-4838-8996-101568d6941e___JR_HL 9732.JPG</path>
	<source>
		<database>Unknown</database>
	</source>
	<size>
		<width>256</width>
		<height>256</height>
		<depth>3</depth>
	</size>
	<segmented>0</segmented>
	<object>
		<name>ch</name>
		<pose>Unspecified</pose>
		<truncated>0</truncated>
		<difficult>0</difficult>
		<bndbox>
			<xmin>28</xmin>
			<ymin>81</ymin>
			<xmax>237</xmax>
			<ymax>213</ymax>
		</bndbox>
	</object>
	<object>
		<name>ch</name>
		<pose>Unspecified</pose>
		<truncated>0</truncated>
		<difficult>0</difficult>
		<bndbox>
			<xmin>57</xmin>
			<ymin>5</ymin>
			<xmax>225</xmax>
			<ymax>83</ymax>
		</bndbox>
	</object>
</annotation>
