<annotation>
	<folder>Tomato___Tomato_Yellow_Leaf_Curl_Virus</folder>
	<filename>1ff892dc-1ab8-453f-ae97-61395b75c036___YLCV_GCREC 2903.JPG</filename>
	<path>C:\Users\TimmySagacity\Desktop\Plant diseases\PlantVillage\train\Tomato___Tomato_Yellow_Leaf_Curl_Virus\1ff892dc-1ab8-453f-ae97-61395b75c036___YLCV_GCREC 2903.JPG</path>
	<source>
		<database>Unknown</database>
	</source>
	<size>
		<width>256</width>
		<height>256</height>
		<depth>3</depth>
	</size>
	<segmented>0</segmented>
	<object>
		<name>t_ty</name>
		<pose>Unspecified</pose>
		<truncated>0</truncated>
		<difficult>0</difficult>
		<bndbox>
			<xmin>19</xmin>
			<ymin>96</ymin>
			<xmax>203</xmax>
			<ymax>240</ymax>
		</bndbox>
	</object>
	<object>
		<name>t_ty</name>
		<pose>Unspecified</pose>
		<truncated>0</truncated>
		<difficult>0</difficult>
		<bndbox>
			<xmin>43</xmin>
			<ymin>10</ymin>
			<xmax>190</xmax>
			<ymax>96</ymax>
		</bndbox>
	</object>
</annotation>
