<annotation>
	<folder>Raspberry___healthy</folder>
	<filename>27542f80-1341-427b-8376-f34255e93092___Mary_HL 6300.JPG</filename>
	<path>C:\Users\TimmySagacity\Desktop\Plant diseases\PlantVillage\train\Raspberry___healthy\27542f80-1341-427b-8376-f34255e93092___Mary_HL 6300.JPG</path>
	<source>
		<database>Unknown</database>
	</source>
	<size>
		<width>256</width>
		<height>256</height>
		<depth>3</depth>
	</size>
	<segmented>0</segmented>
	<object>
		<name>rasp_h</name>
		<pose>Unspecified</pose>
		<truncated>0</truncated>
		<difficult>0</difficult>
		<bndbox>
			<xmin>12</xmin>
			<ymin>113</ymin>
			<xmax>221</xmax>
			<ymax>246</ymax>
		</bndbox>
	</object>
	<object>
		<name>rasp_h</name>
		<pose>Unspecified</pose>
		<truncated>0</truncated>
		<difficult>0</difficult>
		<bndbox>
			<xmin>89</xmin>
			<ymin>6</ymin>
			<xmax>236</xmax>
			<ymax>114</ymax>
		</bndbox>
	</object>
</annotation>
