<annotation>
	<folder>Peach___healthy</folder>
	<filename>38017dc9-d4a9-48d5-9e41-3f3ee90f4c1a___Rutg._HL 3754.JPG</filename>
	<path>C:\Users\TimmySagacity\Desktop\Plant diseases\PlantVillage\train\Peach___healthy\38017dc9-d4a9-48d5-9e41-3f3ee90f4c1a___Rutg._HL 3754.JPG</path>
	<source>
		<database>Unknown</database>
	</source>
	<size>
		<width>256</width>
		<height>256</height>
		<depth>3</depth>
	</size>
	<segmented>0</segmented>
	<object>
		<name>peach_h</name>
		<pose>Unspecified</pose>
		<truncated>0</truncated>
		<difficult>0</difficult>
		<bndbox>
			<xmin>50</xmin>
			<ymin>3</ymin>
			<xmax>165</xmax>
			<ymax>139</ymax>
		</bndbox>
	</object>
	<object>
		<name>peach_h</name>
		<pose>Unspecified</pose>
		<truncated>0</truncated>
		<difficult>0</difficult>
		<bndbox>
			<xmin>68</xmin>
			<ymin>139</ymin>
			<xmax>230</xmax>
			<ymax>249</ymax>
		</bndbox>
	</object>
</annotation>
