<annotation>
	<folder>Apple___Black_rot</folder>
	<filename>50755673-3ea3-4e06-acbb-703413571a91___JR_FrgE.S 2879.JPG</filename>
	<path>C:\Users\TimmySagacity\Desktop\Plant diseases\PlantVillage\train\Apple___Black_rot\50755673-3ea3-4e06-acbb-703413571a91___JR_FrgE.S 2879.JPG</path>
	<source>
		<database>Unknown</database>
	</source>
	<size>
		<width>256</width>
		<height>256</height>
		<depth>3</depth>
	</size>
	<segmented>0</segmented>
	<object>
		<name>abr</name>
		<pose>Unspecified</pose>
		<truncated>0</truncated>
		<difficult>0</difficult>
		<bndbox>
			<xmin>112</xmin>
			<ymin>15</ymin>
			<xmax>237</xmax>
			<ymax>175</ymax>
		</bndbox>
	</object>
</annotation>
