<annotation>
	<folder>Tomato___Bacterial_spot</folder>
	<filename>53d941ee-48e5-4669-8cf4-7a04fb68e808___GCREC_Bact.Sp 5893.JPG</filename>
	<path>C:\Users\TimmySagacity\Desktop\Plant diseases\PlantVillage\train\Tomato___Bacterial_spot\53d941ee-48e5-4669-8cf4-7a04fb68e808___GCREC_Bact.Sp 5893.JPG</path>
	<source>
		<database>Unknown</database>
	</source>
	<size>
		<width>256</width>
		<height>256</height>
		<depth>3</depth>
	</size>
	<segmented>0</segmented>
	<object>
		<name>tom_bs</name>
		<pose>Unspecified</pose>
		<truncated>1</truncated>
		<difficult>0</difficult>
		<bndbox>
			<xmin>21</xmin>
			<ymin>105</ymin>
			<xmax>238</xmax>
			<ymax>256</ymax>
		</bndbox>
	</object>
	<object>
		<name>tom_bs</name>
		<pose>Unspecified</pose>
		<truncated>0</truncated>
		<difficult>0</difficult>
		<bndbox>
			<xmin>53</xmin>
			<ymin>4</ymin>
			<xmax>200</xmax>
			<ymax>105</ymax>
		</bndbox>
	</object>
</annotation>
