<annotation>
	<folder>Tomato___Septoria_leaf_spot</folder>
	<filename>57f2b102-2002-4421-b303-13d75a164fd9___Matt.S_CG 7694.JPG</filename>
	<path>C:\Users\TimmySagacity\Desktop\Plant diseases\PlantVillage\train\Tomato___Septoria_leaf_spot\57f2b102-2002-4421-b303-13d75a164fd9___Matt.S_CG 7694.JPG</path>
	<source>
		<database>Unknown</database>
	</source>
	<size>
		<width>256</width>
		<height>256</height>
		<depth>3</depth>
	</size>
	<segmented>0</segmented>
	<object>
		<name>t_sLs</name>
		<pose>Unspecified</pose>
		<truncated>0</truncated>
		<difficult>0</difficult>
		<bndbox>
			<xmin>55</xmin>
			<ymin>98</ymin>
			<xmax>187</xmax>
			<ymax>178</ymax>
		</bndbox>
	</object>
	<object>
		<name>t_sLs</name>
		<pose>Unspecified</pose>
		<truncated>0</truncated>
		<difficult>0</difficult>
		<bndbox>
			<xmin>158</xmin>
			<ymin>4</ymin>
			<xmax>243</xmax>
			<ymax>104</ymax>
		</bndbox>
	</object>
	<object>
		<name>t_sLs</name>
		<pose>Unspecified</pose>
		<truncated>0</truncated>
		<difficult>0</difficult>
		<bndbox>
			<xmin>99</xmin>
			<ymin>62</ymin>
			<xmax>158</xmax>
			<ymax>97</ymax>
		</bndbox>
	</object>
</annotation>
