<annotation>
	<folder>Tomato___Septoria_leaf_spot</folder>
	<filename>59a17e56-9717-4eaa-857d-e7511f00b633___Matt.S_CG 1027.JPG</filename>
	<path>C:\Users\TimmySagacity\Desktop\Plant diseases\PlantVillage\train\Tomato___Septoria_leaf_spot\59a17e56-9717-4eaa-857d-e7511f00b633___Matt.S_CG 1027.JPG</path>
	<source>
		<database>Unknown</database>
	</source>
	<size>
		<width>256</width>
		<height>256</height>
		<depth>3</depth>
	</size>
	<segmented>0</segmented>
	<object>
		<name>t_sLs</name>
		<pose>Unspecified</pose>
		<truncated>0</truncated>
		<difficult>0</difficult>
		<bndbox>
			<xmin>11</xmin>
			<ymin>143</ymin>
			<xmax>232</xmax>
			<ymax>203</ymax>
		</bndbox>
	</object>
	<object>
		<name>t_sLs</name>
		<pose>Unspecified</pose>
		<truncated>0</truncated>
		<difficult>0</difficult>
		<bndbox>
			<xmin>150</xmin>
			<ymin>223</ymin>
			<xmax>218</xmax>
			<ymax>250</ymax>
		</bndbox>
	</object>
	<object>
		<name>t_sLs</name>
		<pose>Unspecified</pose>
		<truncated>0</truncated>
		<difficult>0</difficult>
		<bndbox>
			<xmin>44</xmin>
			<ymin>75</ymin>
			<xmax>240</xmax>
			<ymax>144</ymax>
		</bndbox>
	</object>
	<object>
		<name>t_sLs</name>
		<pose>Unspecified</pose>
		<truncated>0</truncated>
		<difficult>0</difficult>
		<bndbox>
			<xmin>59</xmin>
			<ymin>4</ymin>
			<xmax>162</xmax>
			<ymax>75</ymax>
		</bndbox>
	</object>
</annotation>
