<annotation>
	<folder>Cherry_(including_sour)___Powdery_mildew</folder>
	<filename>5ae4a221-ce07-4cd5-92fa-e486a14c577f___FREC_Pwd.M 0466.JPG</filename>
	<path>C:\Users\TimmySagacity\Desktop\Plant diseases\PlantVillage\train\Cherry_(including_sour)___Powdery_mildew\5ae4a221-ce07-4cd5-92fa-e486a14c577f___FREC_Pwd.M 0466.JPG</path>
	<source>
		<database>Unknown</database>
	</source>
	<size>
		<width>256</width>
		<height>256</height>
		<depth>3</depth>
	</size>
	<segmented>0</segmented>
	<object>
		<name>cpm</name>
		<pose>Unspecified</pose>
		<truncated>0</truncated>
		<difficult>0</difficult>
		<bndbox>
			<xmin>50</xmin>
			<ymin>50</ymin>
			<xmax>228</xmax>
			<ymax>199</ymax>
		</bndbox>
	</object>
	<object>
		<name>cpm</name>
		<pose>Unspecified</pose>
		<truncated>0</truncated>
		<difficult>0</difficult>
		<bndbox>
			<xmin>16</xmin>
			<ymin>2</ymin>
			<xmax>179</xmax>
			<ymax>53</ymax>
		</bndbox>
	</object>
</annotation>
