<annotation>
	<folder>Apple___healthy</folder>
	<filename>75b7a5bc-e419-4312-b5d9-6c3446a24ef4___RS_HL 6079.JPG</filename>
	<path>C:\Users\TimmySagacity\Desktop\Plant diseases\PlantVillage\train\Apple___healthy\75b7a5bc-e419-4312-b5d9-6c3446a24ef4___RS_HL 6079.JPG</path>
	<source>
		<database>Unknown</database>
	</source>
	<size>
		<width>256</width>
		<height>256</height>
		<depth>3</depth>
	</size>
	<segmented>0</segmented>
	<object>
		<name>ah</name>
		<pose>Unspecified</pose>
		<truncated>0</truncated>
		<difficult>0</difficult>
		<bndbox>
			<xmin>58</xmin>
			<ymin>5</ymin>
			<xmax>239</xmax>
			<ymax>226</ymax>
		</bndbox>
	</object>
</annotation>
