<annotation>
	<folder>Potato___Early_blight</folder>
	<filename>7795f733-eeb0-4353-bdb8-b2f4d8d622d4___RS_Early.B 6960.JPG</filename>
	<path>C:\Users\TimmySagacity\Desktop\Plant diseases\PlantVillage\train\Potato___Early_blight\7795f733-eeb0-4353-bdb8-b2f4d8d622d4___RS_Early.B 6960.JPG</path>
	<source>
		<database>Unknown</database>
	</source>
	<size>
		<width>256</width>
		<height>256</height>
		<depth>3</depth>
	</size>
	<segmented>0</segmented>
	<object>
		<name>po_eb</name>
		<pose>Unspecified</pose>
		<truncated>0</truncated>
		<difficult>0</difficult>
		<bndbox>
			<xmin>24</xmin>
			<ymin>93</ymin>
			<xmax>248</xmax>
			<ymax>248</ymax>
		</bndbox>
	</object>
	<object>
		<name>po_eb</name>
		<pose>Unspecified</pose>
		<truncated>0</truncated>
		<difficult>0</difficult>
		<bndbox>
			<xmin>81</xmin>
			<ymin>10</ymin>
			<xmax>248</xmax>
			<ymax>93</ymax>
		</bndbox>
	</object>
</annotation>
