<annotation>
	<folder>Tomato___Spider_mites Two-spotted_spider_mite</folder>
	<filename>7bb0ee74-55e4-45df-88e5-9545947aa7c2___Com.G_SpM_FL 9468.JPG</filename>
	<path>C:\Users\TimmySagacity\Desktop\Plant diseases\PlantVillage\train\Tomato___Spider_mites Two-spotted_spider_mite\7bb0ee74-55e4-45df-88e5-9545947aa7c2___Com.G_SpM_FL 9468.JPG</path>
	<source>
		<database>Unknown</database>
	</source>
	<size>
		<width>256</width>
		<height>256</height>
		<depth>3</depth>
	</size>
	<segmented>0</segmented>
	<object>
		<name>t_smt</name>
		<pose>Unspecified</pose>
		<truncated>0</truncated>
		<difficult>0</difficult>
		<bndbox>
			<xmin>36</xmin>
			<ymin>133</ymin>
			<xmax>191</xmax>
			<ymax>244</ymax>
		</bndbox>
	</object>
	<object>
		<name>t_smt</name>
		<pose>Unspecified</pose>
		<truncated>0</truncated>
		<difficult>0</difficult>
		<bndbox>
			<xmin>53</xmin>
			<ymin>69</ymin>
			<xmax>174</xmax>
			<ymax>133</ymax>
		</bndbox>
	</object>
	<object>
		<name>t_smt</name>
		<pose>Unspecified</pose>
		<truncated>0</truncated>
		<difficult>0</difficult>
		<bndbox>
			<xmin>76</xmin>
			<ymin>18</ymin>
			<xmax>135</xmax>
			<ymax>70</ymax>
		</bndbox>
	</object>
</annotation>
