<annotation>
	<folder>Peach___healthy</folder>
	<filename>7cfd0ac5-2c8a-4a59-ab0f-822e77d96060___Rutg._HL 3632.JPG</filename>
	<path>C:\Users\TimmySagacity\Desktop\Plant diseases\PlantVillage\train\Peach___healthy\7cfd0ac5-2c8a-4a59-ab0f-822e77d96060___Rutg._HL 3632.JPG</path>
	<source>
		<database>Unknown</database>
	</source>
	<size>
		<width>256</width>
		<height>256</height>
		<depth>3</depth>
	</size>
	<segmented>0</segmented>
	<object>
		<name>peach_h</name>
		<pose>Unspecified</pose>
		<truncated>0</truncated>
		<difficult>0</difficult>
		<bndbox>
			<xmin>13</xmin>
			<ymin>147</ymin>
			<xmax>143</xmax>
			<ymax>229</ymax>
		</bndbox>
	</object>
	<object>
		<name>peach_h</name>
		<pose>Unspecified</pose>
		<truncated>0</truncated>
		<difficult>0</difficult>
		<bndbox>
			<xmin>137</xmin>
			<ymin>45</ymin>
			<xmax>210</xmax>
			<ymax>148</ymax>
		</bndbox>
	</object>
	<object>
		<name>peach_h</name>
		<pose>Unspecified</pose>
		<truncated>0</truncated>
		<difficult>0</difficult>
		<bndbox>
			<xmin>74</xmin>
			<ymin>48</ymin>
			<xmax>138</xmax>
			<ymax>146</ymax>
		</bndbox>
	</object>
	<object>
		<name>peach_h</name>
		<pose>Unspecified</pose>
		<truncated>1</truncated>
		<difficult>0</difficult>
		<bndbox>
			<xmin>148</xmin>
			<ymin>1</ymin>
			<xmax>245</xmax>
			<ymax>45</ymax>
		</bndbox>
	</object>
</annotation>
