<annotation>
	<folder>Pepper,_bell___Bacterial_spot</folder>
	<filename>afd0c913-1e90-4ff9-9a61-bd0a5297c012___JR_B.Spot 3221.JPG</filename>
	<path>C:\Users\TimmySagacity\Desktop\Plant diseases\PlantVillage\train\Pepper,_bell___Bacterial_spot\afd0c913-1e90-4ff9-9a61-bd0a5297c012___JR_B.Spot 3221.JPG</path>
	<source>
		<database>Unknown</database>
	</source>
	<size>
		<width>256</width>
		<height>256</height>
		<depth>3</depth>
	</size>
	<segmented>0</segmented>
	<object>
		<name>pp_bs</name>
		<pose>Unspecified</pose>
		<truncated>0</truncated>
		<difficult>0</difficult>
		<bndbox>
			<xmin>13</xmin>
			<ymin>134</ymin>
			<xmax>248</xmax>
			<ymax>235</ymax>
		</bndbox>
	</object>
	<object>
		<name>pp_bs</name>
		<pose>Unspecified</pose>
		<truncated>0</truncated>
		<difficult>0</difficult>
		<bndbox>
			<xmin>19</xmin>
			<ymin>63</ymin>
			<xmax>240</xmax>
			<ymax>134</ymax>
		</bndbox>
	</object>
	<object>
		<name>pp_bs</name>
		<pose>Unspecified</pose>
		<truncated>0</truncated>
		<difficult>0</difficult>
		<bndbox>
			<xmin>78</xmin>
			<ymin>2</ymin>
			<xmax>236</xmax>
			<ymax>64</ymax>
		</bndbox>
	</object>
</annotation>
