<annotation>
	<folder>Cherry_(including_sour)___healthy</folder>
	<filename>c376780a-87fa-4d3b-851c-ee98da3d6950___JR_HL 9430.JPG</filename>
	<path>C:\Users\TimmySagacity\Desktop\Plant diseases\PlantVillage\train\Cherry_(including_sour)___healthy\c376780a-87fa-4d3b-851c-ee98da3d6950___JR_HL 9430.JPG</path>
	<source>
		<database>Unknown</database>
	</source>
	<size>
		<width>256</width>
		<height>256</height>
		<depth>3</depth>
	</size>
	<segmented>0</segmented>
	<object>
		<name>ch</name>
		<pose>Unspecified</pose>
		<truncated>0</truncated>
		<difficult>0</difficult>
		<bndbox>
			<xmin>37</xmin>
			<ymin>6</ymin>
			<xmax>240</xmax>
			<ymax>206</ymax>
		</bndbox>
	</object>
</annotation>
