<annotation>
	<folder>Tomato___Target_Spot</folder>
	<filename>0c91af09-0ad7-46a1-844b-edfd6af34df2___Com.G_TgS_FL 9776.JPG</filename>
	<path>C:\Users\TimmySagacity\Desktop\Plant diseases\PlantVillage\train\Tomato___Target_Spot\0c91af09-0ad7-46a1-844b-edfd6af34df2___Com.G_TgS_FL 9776.JPG</path>
	<source>
		<database>Unknown</database>
	</source>
	<size>
		<width>256</width>
		<height>256</height>
		<depth>3</depth>
	</size>
	<segmented>0</segmented>
	<object>
		<name>t_ts</name>
		<pose>Unspecified</pose>
		<truncated>0</truncated>
		<difficult>0</difficult>
		<bndbox>
			<xmin>38</xmin>
			<ymin>151</ymin>
			<xmax>233</xmax>
			<ymax>236</ymax>
		</bndbox>
	</object>
	<object>
		<name>t_ts</name>
		<pose>Unspecified</pose>
		<truncated>0</truncated>
		<difficult>0</difficult>
		<bndbox>
			<xmin>63</xmin>
			<ymin>67</ymin>
			<xmax>209</xmax>
			<ymax>152</ymax>
		</bndbox>
	</object>
	<object>
		<name>t_ts</name>
		<pose>Unspecified</pose>
		<truncated>0</truncated>
		<difficult>0</difficult>
		<bndbox>
			<xmin>94</xmin>
			<ymin>23</ymin>
			<xmax>189</xmax>
			<ymax>67</ymax>
		</bndbox>
	</object>
</annotation>
