<annotation>
	<folder>Apple___Black_rot</folder>
	<filename>3235339f-7b7b-423a-850a-0fd58ded4725___JR_FrgE.S 2791.JPG</filename>
	<path>C:\Users\TimmySagacity\Desktop\Plant diseases\PlantVillage\train\Apple___Black_rot\3235339f-7b7b-423a-850a-0fd58ded4725___JR_FrgE.S 2791.JPG</path>
	<source>
		<database>Unknown</database>
	</source>
	<size>
		<width>256</width>
		<height>256</height>
		<depth>3</depth>
	</size>
	<segmented>0</segmented>
	<object>
		<name>abr</name>
		<pose>Unspecified</pose>
		<truncated>0</truncated>
		<difficult>0</difficult>
		<bndbox>
			<xmin>26</xmin>
			<ymin>15</ymin>
			<xmax>234</xmax>
			<ymax>236</ymax>
		</bndbox>
	</object>
</annotation>
