<annotation>
	<folder>Tomato___Target_Spot</folder>
	<filename>34f1271d-c6e9-4247-a6ba-2e493343d2ac___Com.G_TgS_FL 8069.JPG</filename>
	<path>C:\Users\TimmySagacity\Desktop\Plant diseases\PlantVillage\train\Tomato___Target_Spot\34f1271d-c6e9-4247-a6ba-2e493343d2ac___Com.G_TgS_FL 8069.JPG</path>
	<source>
		<database>Unknown</database>
	</source>
	<size>
		<width>256</width>
		<height>256</height>
		<depth>3</depth>
	</size>
	<segmented>0</segmented>
	<object>
		<name>t_ts</name>
		<pose>Unspecified</pose>
		<truncated>0</truncated>
		<difficult>0</difficult>
		<bndbox>
			<xmin>61</xmin>
			<ymin>103</ymin>
			<xmax>190</xmax>
			<ymax>177</ymax>
		</bndbox>
	</object>
	<object>
		<name>t_ts</name>
		<pose>Unspecified</pose>
		<truncated>0</truncated>
		<difficult>0</difficult>
		<bndbox>
			<xmin>100</xmin>
			<ymin>10</ymin>
			<xmax>161</xmax>
			<ymax>105</ymax>
		</bndbox>
	</object>
</annotation>
