<annotation>
	<folder>Cherry_(including_sour)___healthy</folder>
	<filename>3f71f4e4-5aa2-4706-8cd1-8608f5ae6215___JR_HL 9669.JPG</filename>
	<path>C:\Users\TimmySagacity\Desktop\Plant diseases\PlantVillage\train\Cherry_(including_sour)___healthy\3f71f4e4-5aa2-4706-8cd1-8608f5ae6215___JR_HL 9669.JPG</path>
	<source>
		<database>Unknown</database>
	</source>
	<size>
		<width>256</width>
		<height>256</height>
		<depth>3</depth>
	</size>
	<segmented>0</segmented>
	<object>
		<name>ch</name>
		<pose>Unspecified</pose>
		<truncated>0</truncated>
		<difficult>0</difficult>
		<bndbox>
			<xmin>27</xmin>
			<ymin>125</ymin>
			<xmax>233</xmax>
			<ymax>240</ymax>
		</bndbox>
	</object>
	<object>
		<name>ch</name>
		<pose>Unspecified</pose>
		<truncated>0</truncated>
		<difficult>0</difficult>
		<bndbox>
			<xmin>48</xmin>
			<ymin>65</ymin>
			<xmax>240</xmax>
			<ymax>125</ymax>
		</bndbox>
	</object>
	<object>
		<name>ch</name>
		<pose>Unspecified</pose>
		<truncated>0</truncated>
		<difficult>0</difficult>
		<bndbox>
			<xmin>118</xmin>
			<ymin>7</ymin>
			<xmax>241</xmax>
			<ymax>66</ymax>
		</bndbox>
	</object>
</annotation>
