<annotation>
	<folder>Tomato___Leaf_Mold</folder>
	<filename>55c2cd78-8c7c-4102-801f-c87d2284b874___Crnl_L.Mold 7069.JPG</filename>
	<path>C:\Users\TimmySagacity\Desktop\Plant diseases\PlantVillage\train\Tomato___Leaf_Mold\55c2cd78-8c7c-4102-801f-c87d2284b874___Crnl_L.Mold 7069.JPG</path>
	<source>
		<database>Unknown</database>
	</source>
	<size>
		<width>256</width>
		<height>256</height>
		<depth>3</depth>
	</size>
	<segmented>0</segmented>
	<object>
		<name>tom_Lm</name>
		<pose>Unspecified</pose>
		<truncated>0</truncated>
		<difficult>0</difficult>
		<bndbox>
			<xmin>39</xmin>
			<ymin>16</ymin>
			<xmax>208</xmax>
			<ymax>235</ymax>
		</bndbox>
	</object>
</annotation>
