<annotation>
	<folder>Tomato___Leaf_Mold</folder>
	<filename>5d0e582a-7d32-4069-9987-468d87614c8f___Crnl_L.Mold 9138.JPG</filename>
	<path>C:\Users\TimmySagacity\Desktop\Plant diseases\PlantVillage\train\Tomato___Leaf_Mold\5d0e582a-7d32-4069-9987-468d87614c8f___Crnl_L.Mold 9138.JPG</path>
	<source>
		<database>Unknown</database>
	</source>
	<size>
		<width>256</width>
		<height>256</height>
		<depth>3</depth>
	</size>
	<segmented>0</segmented>
	<object>
		<name>tom_Lm</name>
		<pose>Unspecified</pose>
		<truncated>0</truncated>
		<difficult>0</difficult>
		<bndbox>
			<xmin>71</xmin>
			<ymin>92</ymin>
			<xmax>219</xmax>
			<ymax>234</ymax>
		</bndbox>
	</object>
	<object>
		<name>tom_Lm</name>
		<pose>Unspecified</pose>
		<truncated>1</truncated>
		<difficult>0</difficult>
		<bndbox>
			<xmin>156</xmin>
			<ymin>1</ymin>
			<xmax>236</xmax>
			<ymax>92</ymax>
		</bndbox>
	</object>
</annotation>
