<annotation>
	<folder>Peach___Bacterial_spot</folder>
	<filename>5dbe70fd-fce9-450d-93fc-9e98a279e7ee___Rutg._Bact.S 1887.JPG</filename>
	<path>C:\Users\TimmySagacity\Desktop\Plant diseases\PlantVillage\train\Peach___Bacterial_spot\5dbe70fd-fce9-450d-93fc-9e98a279e7ee___Rutg._Bact.S 1887.JPG</path>
	<source>
		<database>Unknown</database>
	</source>
	<size>
		<width>256</width>
		<height>256</height>
		<depth>3</depth>
	</size>
	<segmented>0</segmented>
	<object>
		<name>pbs</name>
		<pose>Unspecified</pose>
		<truncated>0</truncated>
		<difficult>0</difficult>
		<bndbox>
			<xmin>47</xmin>
			<ymin>9</ymin>
			<xmax>166</xmax>
			<ymax>90</ymax>
		</bndbox>
	</object>
	<object>
		<name>pbs</name>
		<pose>Unspecified</pose>
		<truncated>0</truncated>
		<difficult>0</difficult>
		<bndbox>
			<xmin>70</xmin>
			<ymin>90</ymin>
			<xmax>203</xmax>
			<ymax>148</ymax>
		</bndbox>
	</object>
	<object>
		<name>pbs</name>
		<pose>Unspecified</pose>
		<truncated>0</truncated>
		<difficult>0</difficult>
		<bndbox>
			<xmin>89</xmin>
			<ymin>149</ymin>
			<xmax>206</xmax>
			<ymax>242</ymax>
		</bndbox>
	</object>
</annotation>
