<annotation>
	<folder>Squash___Powdery_mildew</folder>
	<filename>62b0096f-065c-44e4-a760-44712adfa767___UMD_Powd.M 0082.JPG</filename>
	<path>C:\Users\TimmySagacity\Desktop\Plant diseases\PlantVillage\train\Squash___Powdery_mildew\62b0096f-065c-44e4-a760-44712adfa767___UMD_Powd.M 0082.JPG</path>
	<source>
		<database>Unknown</database>
	</source>
	<size>
		<width>256</width>
		<height>256</height>
		<depth>3</depth>
	</size>
	<segmented>0</segmented>
	<object>
		<name>squ_pm</name>
		<pose>Unspecified</pose>
		<truncated>1</truncated>
		<difficult>0</difficult>
		<bndbox>
			<xmin>1</xmin>
			<ymin>1</ymin>
			<xmax>256</xmax>
			<ymax>124</ymax>
		</bndbox>
	</object>
	<object>
		<name>squ_pm</name>
		<pose>Unspecified</pose>
		<truncated>1</truncated>
		<difficult>0</difficult>
		<bndbox>
			<xmin>22</xmin>
			<ymin>124</ymin>
			<xmax>247</xmax>
			<ymax>256</ymax>
		</bndbox>
	</object>
</annotation>
