<annotation>
	<folder>Pepper,_bell___Bacterial_spot</folder>
	<filename>64ed4b17-84ad-4088-b079-c02eceef5e7e___NREC_B.Spot 1958.JPG</filename>
	<path>C:\Users\TimmySagacity\Desktop\Plant diseases\PlantVillage\train\Pepper,_bell___Bacterial_spot\64ed4b17-84ad-4088-b079-c02eceef5e7e___NREC_B.Spot 1958.JPG</path>
	<source>
		<database>Unknown</database>
	</source>
	<size>
		<width>256</width>
		<height>256</height>
		<depth>3</depth>
	</size>
	<segmented>0</segmented>
	<object>
		<name>pp_bs</name>
		<pose>Unspecified</pose>
		<truncated>0</truncated>
		<difficult>0</difficult>
		<bndbox>
			<xmin>7</xmin>
			<ymin>61</ymin>
			<xmax>115</xmax>
			<ymax>134</ymax>
		</bndbox>
	</object>
	<object>
		<name>pp_bs</name>
		<pose>Unspecified</pose>
		<truncated>0</truncated>
		<difficult>0</difficult>
		<bndbox>
			<xmin>70</xmin>
			<ymin>135</ymin>
			<xmax>218</xmax>
			<ymax>250</ymax>
		</bndbox>
	</object>
	<object>
		<name>pp_bs</name>
		<pose>Unspecified</pose>
		<truncated>0</truncated>
		<difficult>0</difficult>
		<bndbox>
			<xmin>116</xmin>
			<ymin>105</ymin>
			<xmax>221</xmax>
			<ymax>136</ymax>
		</bndbox>
	</object>
	<object>
		<name>pp_bs</name>
		<pose>Unspecified</pose>
		<truncated>0</truncated>
		<difficult>0</difficult>
		<bndbox>
			<xmin>150</xmin>
			<ymin>11</ymin>
			<xmax>238</xmax>
			<ymax>105</ymax>
		</bndbox>
	</object>
</annotation>
