<annotation>
	<folder>Strawberry___Leaf_scorch</folder>
	<filename>66e1a9d0-bca6-4c01-89c7-00cc0acbe810___RS_L.Scorch 1156.JPG</filename>
	<path>C:\Users\TimmySagacity\Desktop\Plant diseases\PlantVillage\train\Strawberry___Leaf_scorch\66e1a9d0-bca6-4c01-89c7-00cc0acbe810___RS_L.Scorch 1156.JPG</path>
	<source>
		<database>Unknown</database>
	</source>
	<size>
		<width>256</width>
		<height>256</height>
		<depth>3</depth>
	</size>
	<segmented>0</segmented>
	<object>
		<name>sberry_Ls</name>
		<pose>Unspecified</pose>
		<truncated>0</truncated>
		<difficult>0</difficult>
		<bndbox>
			<xmin>11</xmin>
			<ymin>23</ymin>
			<xmax>242</xmax>
			<ymax>208</ymax>
		</bndbox>
	</object>
</annotation>
