<annotation>
	<folder>Apple___Apple_scab</folder>
	<filename>74813834-38bc-4301-93ff-39b208eb52bc___FREC_Scab 3315.JPG</filename>
	<path>C:\Users\TimmySagacity\Desktop\Plant diseases\PlantVillage\train\Apple___Apple_scab\74813834-38bc-4301-93ff-39b208eb52bc___FREC_Scab 3315.JPG</path>
	<source>
		<database>Unknown</database>
	</source>
	<size>
		<width>256</width>
		<height>256</height>
		<depth>3</depth>
	</size>
	<segmented>0</segmented>
	<object>
		<name>as</name>
		<pose>Unspecified</pose>
		<truncated>0</truncated>
		<difficult>0</difficult>
		<bndbox>
			<xmin>46</xmin>
			<ymin>8</ymin>
			<xmax>255</xmax>
			<ymax>127</ymax>
		</bndbox>
	</object>
	<object>
		<name>as</name>
		<pose>Unspecified</pose>
		<truncated>1</truncated>
		<difficult>0</difficult>
		<bndbox>
			<xmin>2</xmin>
			<ymin>124</ymin>
			<xmax>209</xmax>
			<ymax>256</ymax>
		</bndbox>
	</object>
</annotation>
