<annotation>
	<folder>Peach___Bacterial_spot</folder>
	<filename>7a150d22-e5ed-4dee-9584-52650f59ab33___Rut._Bact.S 1520.JPG</filename>
	<path>C:\Users\TimmySagacity\Desktop\Plant diseases\PlantVillage\train\Peach___Bacterial_spot\7a150d22-e5ed-4dee-9584-52650f59ab33___Rut._Bact.S 1520.JPG</path>
	<source>
		<database>Unknown</database>
	</source>
	<size>
		<width>256</width>
		<height>256</height>
		<depth>3</depth>
	</size>
	<segmented>0</segmented>
	<object>
		<name>pbs</name>
		<pose>Unspecified</pose>
		<truncated>0</truncated>
		<difficult>0</difficult>
		<bndbox>
			<xmin>9</xmin>
			<ymin>150</ymin>
			<xmax>81</xmax>
			<ymax>221</ymax>
		</bndbox>
	</object>
	<object>
		<name>pbs</name>
		<pose>Unspecified</pose>
		<truncated>0</truncated>
		<difficult>0</difficult>
		<bndbox>
			<xmin>94</xmin>
			<ymin>79</ymin>
			<xmax>198</xmax>
			<ymax>161</ymax>
		</bndbox>
	</object>
	<object>
		<name>pbs</name>
		<pose>Unspecified</pose>
		<truncated>0</truncated>
		<difficult>0</difficult>
		<bndbox>
			<xmin>157</xmin>
			<ymin>5</ymin>
			<xmax>249</xmax>
			<ymax>74</ymax>
		</bndbox>
	</object>
</annotation>
