<annotation>
	<folder>Pepper,_bell___healthy</folder>
	<filename>8e8ad705-85d5-407a-b439-1464cb166e34___JR_HL 7924.JPG</filename>
	<path>C:\Users\TimmySagacity\Desktop\Plant diseases\PlantVillage\train\Pepper,_bell___healthy\8e8ad705-85d5-407a-b439-1464cb166e34___JR_HL 7924.JPG</path>
	<source>
		<database>Unknown</database>
	</source>
	<size>
		<width>256</width>
		<height>256</height>
		<depth>3</depth>
	</size>
	<segmented>0</segmented>
	<object>
		<name>pp_h</name>
		<pose>Unspecified</pose>
		<truncated>0</truncated>
		<difficult>0</difficult>
		<bndbox>
			<xmin>9</xmin>
			<ymin>107</ymin>
			<xmax>241</xmax>
			<ymax>247</ymax>
		</bndbox>
	</object>
	<object>
		<name>pp_h</name>
		<pose>Unspecified</pose>
		<truncated>0</truncated>
		<difficult>0</difficult>
		<bndbox>
			<xmin>59</xmin>
			<ymin>21</ymin>
			<xmax>197</xmax>
			<ymax>108</ymax>
		</bndbox>
	</object>
</annotation>
