<annotation>
	<folder>Tomato___Leaf_Mold</folder>
	<filename>8e92b724-a066-4039-a090-2699c5cfed4e___Crnl_L.Mold 6724.JPG</filename>
	<path>C:\Users\TimmySagacity\Desktop\Plant diseases\PlantVillage\train\Tomato___Leaf_Mold\8e92b724-a066-4039-a090-2699c5cfed4e___Crnl_L.Mold 6724.JPG</path>
	<source>
		<database>Unknown</database>
	</source>
	<size>
		<width>256</width>
		<height>256</height>
		<depth>3</depth>
	</size>
	<segmented>0</segmented>
	<object>
		<name>tom_Lm</name>
		<pose>Unspecified</pose>
		<truncated>0</truncated>
		<difficult>0</difficult>
		<bndbox>
			<xmin>35</xmin>
			<ymin>82</ymin>
			<xmax>207</xmax>
			<ymax>213</ymax>
		</bndbox>
	</object>
	<object>
		<name>tom_Lm</name>
		<pose>Unspecified</pose>
		<truncated>0</truncated>
		<difficult>0</difficult>
		<bndbox>
			<xmin>100</xmin>
			<ymin>25</ymin>
			<xmax>222</xmax>
			<ymax>82</ymax>
		</bndbox>
	</object>
</annotation>
